moblin_assistant.py
moblin_assistant-0.8.0.dist-info/LICENSE
moblin_assistant-0.8.0.dist-info/METADATA
moblin_assistant-0.8.0.dist-info/WHEEL
moblin_assistant-0.8.0.dist-info/entry_points.txt
moblin_assistant-0.8.0.dist-info/top_level.txt
moblin_assistant-0.8.0.dist-info/RECORD
