Metadata-Version: 2.2
Name: moblin_assistant
Version: 0.8.0
Summary: Moblin remote control assistant
Home-page: https://github.com/eerimoq/moblin_assistant
Author: Erik Moqvist
Author-email: erik.moqvist@gmail.com
License: MIT
Classifier: License :: OSI Approved :: MIT License
Classifier: Programming Language :: Python :: 3.9
Requires-Python: >=3.9
License-File: LICENSE
Requires-Dist: aiohttp
Requires-Dist: websockets
Dynamic: author
Dynamic: author-email
Dynamic: classifier
Dynamic: description
Dynamic: home-page
Dynamic: license
Dynamic: requires-dist
Dynamic: requires-python
Dynamic: summary
